[
  {
    "title": "",
    "description": "Nursery",
    "price": 5000,
    "pdfUrl": "https://freshteacher.software/nurseriez/BABY  MATH.pdf"
  },
  {
    "title": "",
    "description": "Nursery",
    "price": 5000,
    "pdfUrl": "https://freshteacher.software/nurseriez/Baby - ASK.pdf"
  },
  {
    "title": "",
    "description": "Nursery",
    "price": 5000,
    "pdfUrl": "https://freshteacher.software/nurseriez/BABY CLASS - ENGLISH.pdf"
  },
  {
    "title": "",
    "description": "Nursery",
    "price": 5000,
    "pdfUrl": "https://freshteacher.software/nurseriez/BABY CLASS ENGLISH HOMEWORK FOR TERM II.pdf"
  },
  {
    "title": "",
    "description": "Nursery",
    "price": 5000,
    "pdfUrl": "https://freshteacher.software/nurseriez/BABY CLASS G.K.pdf"
  },
  {
    "title": "",
    "description": "Nursery",
    "price": 5000,
    "pdfUrl": "https://freshteacher.software/nurseriez/BABY CLASS HOLIDAY PACKAGE.pdf"
  },
  {
    "title": "",
    "description": "Nursery",
    "price": 5000,
    "pdfUrl": "https://freshteacher.software/nurseriez/BABY CLASS READING.pdf"
  },
  {
    "title": "",
    "description": "Nursery",
    "price": 5000,
    "pdfUrl": "https://freshteacher.software/nurseriez/BABY CLASS-READING.pdf"
  },
  {
    "title": "",
    "description": "Nursery",
    "price": 5000,
    "pdfUrl": "https://freshteacher.software/nurseriez/Baby Drawing.pdf"
  },
  {
    "title": "",
    "description": "Nursery",
    "price": 5000,
    "pdfUrl": "https://freshteacher.software/nurseriez/Baby English.pdf"
  },
  {
    "title": "",
    "description": "Nursery",
    "price": 5000,
    "pdfUrl": "https://freshteacher.software/nurseriez/BABY LA.1  MID TERM 1 2023.pdf"
  },
  {
    "title": "",
    "description": "Nursery",
    "price": 5000,
    "pdfUrl": "https://freshteacher.software/nurseriez/BABY LA.2 MID TERM 1 2023.pdf"
  },
  {
    "title": "",
    "description": "Nursery",
    "price": 5000,
    "pdfUrl": "https://freshteacher.software/nurseriez/BABY LA.3 MID TERM 1 2023.pdf"
  },
  {
    "title": "",
    "description": "Nursery",
    "price": 5000,
    "pdfUrl": "https://freshteacher.software/nurseriez/BABY LA.4 MID TERM 1 2023.pdf"
  },
  {
    "title": "",
    "description": "Nursery",
    "price": 5000,
    "pdfUrl": "https://freshteacher.software/nurseriez/BABY LA.5 MID TERM 1 2023.pdf"
  },
  {
    "title": "",
    "description": "Nursery",
    "price": 5000,
    "pdfUrl": "https://freshteacher.software/nurseriez/BABY NUMBERS-1.pdf"
  },
  {
    "title": "",
    "description": "Nursery",
    "price": 5000,
    "pdfUrl": "https://freshteacher.software/nurseriez/Baby Numbers.pdf"
  },
  {
    "title": "",
    "description": "Nursery",
    "price": 5000,
    "pdfUrl": "https://freshteacher.software/nurseriez/Baby Reading.pdf"
  },
  {
    "title": "",
    "description": "Nursery",
    "price": 5000,
    "pdfUrl": "https://freshteacher.software/nurseriez/Baby Social development.pdf"
  },
  {
    "title": "",
    "description": "Nursery",
    "price": 5000,
    "pdfUrl": "https://freshteacher.software/nurseriez/Health Habit baby.pdf"
  },
  {
    "title": "",
    "description": "Nursery",
    "price": 5000,
    "pdfUrl": "https://freshteacher.software/nurseriez/Holiday package baby EOT 1.pdf"
  },
  
  {
        "title": "2016_1-Baby-Class",
        "description": "Baby Class",
        "price": 5000,
        "pdfUrl": "https://freshteacher.software/2016_1-Baby-Class.pdf"
      },
      {
        "title": "BABY CLASS  RECESS PACKAGE, 2020 HORMISDALLEN SCHOOLS",
        "description": "Baby Class",
        "price": 5000,
        "pdfUrl": "https://freshteacher.software/BABY CLASS  RECESS PACKAGE, 2020 HORMISDALLEN SCHOOLS pdf.pdf"
      },
      {
        "title": "BABY CLASS - ENGLISH .1",
        "description": "Baby Class",
        "price": 5000,
        "pdfUrl": "https://freshteacher.software/BABY CLASS - ENGLISH .1.pdf"
      },
      {
        "title": "BABY CLASS - ENGLISH HOLIDAY WORK KINGS SCHOOL KABOWA",
        "description": "Baby Class",
        "price": 5000,
        "pdfUrl": "https://freshteacher.software/BABY CLASS - ENGLISH HOLIDAY WORK KINGS SCHOOL KABOWA.pdf"
      },
      {
        "title": "BABY CLASS - SET THREE",
        "description": "Baby Class",
        "price": 5000,
        "pdfUrl": "https://freshteacher.software/BABY CLASS - SET THREE.pdf"
      },
      {
        "title": "BABY CLASS APTITUDE PRE-JAB EXAM TERM 3 2018",
        "description": "Baby Class",
        "price": 5000,
        "pdfUrl": "https://freshteacher.software/BABY CLASS APTITUDE PRE-JAB EXAM TERM 3 2018.pdf"
      },
      {
        "title": "Baby Class EXERCISES",
        "description": "Baby Class",
        "price": 5000,
        "pdfUrl": "https://freshteacher.software/Baby Class EXERCISES.pdf"
      },
      {
        "title": "BABY CLASS LEARNING AREA 4",
        "description": "Baby Class",
        "price": 5000,
        "pdfUrl": "https://freshteacher.software/BABY CLASS LEARNING AREA 4.pdf"
      },
      {
        "title": "Baby class weekly activity",
        "description": "Baby Class",
        "price": 5000,
        "pdfUrl": "https://freshteacher.software/Baby class weekly activity.pdf"
      },
      {
        "title": "Baby Class WORK 19TH MAY",
        "description": "Baby Class",
        "price": 5000,
        "pdfUrl": "https://freshteacher.software/Baby Class WORK 19TH MAY.pdf"
      },
      {
        "title": "BABY CLASS-LITERACY",
        "description": "Baby Class",
        "price": 5000,
        "pdfUrl": "https://freshteacher.software/BABY CLASS-LITERACY.pdf"
      },
      {
        "title": "BABY CLASS-NUMBERS",
        "description": "Baby Class",
        "price": 5000,
        "pdfUrl": "https://freshteacher.software/BABY CLASS-NUMBERS.pdf"
      },
      {
        "title": "BABY CLASS-READING",
        "description": "Baby Class",
        "price": 5000,
        "pdfUrl": "https://freshteacher.software/BABY CLASS-READING.pdf"
      },
      {
        "title": "BABY CLASS-WRITING HOLIDAY WORK KINGS SCHOOL KABOWA",
        "description": "Baby Class",
        "price": 5000,
        "pdfUrl": "https://freshteacher.software/BABY CLASS-WRITING HOLIDAY WORK KINGS SCHOOL KABOWA.pdf"
      },
      {
        "title": "BABY CLASS-WRITING",
        "description": "Baby Class",
        "price": 5000,
        "pdfUrl": "https://freshteacher.software/BABY CLASS-WRITING.pdf"
      },
      {
        "title": "BABY END OF MARCH EXAMS",
        "description": "Baby Class",
        "price": 5000,
        "pdfUrl": "https://freshteacher.software/BABY END OF MARCH EXAMS.pdf"
      },
      {
        "title": "BABY MID OF TERM III EXAMINATION",
        "description": "Baby Class",
        "price": 5000,
        "pdfUrl": "https://freshteacher.software/BABY MID OF TERM III EXAMINATION.pdf"
      },
      {
        "title": "BABY_CLASS_SET_EIGHT_ENGLISH_WORK_KAMPALA_PARENTS__SCHOOL_2004",
        "description": "Baby Class",
        "price": 5000,
        "pdfUrl": "https://freshteacher.software/BABY_CLASS_SET_EIGHT_ENGLISH_WORK_KAMPALA_PARENTS__SCHOOL_2004.pdf"
      },
      {
        "title": "BABY_CLASS_SET_ELEVEN_ENGLISH_WORK_KAMPALA_PARENTS__SCHOOL_2004",    
        "description": "Baby Class",
        "price": 5000,
        "pdfUrl": "https://freshteacher.software/BABY_CLASS_SET_ELEVEN_ENGLISH_WORK_KAMPALA_PARENTS__SCHOOL_2004.pdf"
      },
      {
        "title": "BABY_CLASS_SET_NINE_ENGLISH_WORK_KAMPALA_PARENTS__SCHOOL_2004",
        "description": "Baby Class",
        "price": 5000,
        "pdfUrl": "https://freshteacher.software/BABY_CLASS_SET_NINE_ENGLISH_WORK_KAMPALA_PARENTS__SCHOOL_2004.pdf"
      },
      {
        "title": "BABY_CLASS_SET_SEVEN_ENGLISH_WORK_KAMPALA_PARENTS__SCHOOL_2004",
        "description": "Baby Class",
        "price": 5000,
        "pdfUrl": "https://freshteacher.software/BABY_CLASS_SET_SEVEN_ENGLISH_WORK_KAMPALA_PARENTS__SCHOOL_2004.pdf"
      },
      {
        "title": "BABY_CLASS_SET_TEN_NUMBER_WORK_KAMPALA_PARENTS__SCHOOL_2004",
        "description": "Baby Class",
        "price": 5000,
        "pdfUrl": "https://freshteacher.software/BABY_CLASS_SET_TEN_NUMBER_WORK_KAMPALA_PARENTS__SCHOOL_2004.pdf"
      },
      {
        "title": "BABY_CLASS_SET_TWELVE_ENGLISH_WORK_KAMPALA_PARENTS__SCHOOL_2004",
        "description": "Baby Class",
        "price": 5000,
        "pdfUrl": "https://freshteacher.software/BABY_CLASS_SET_TWELVE_ENGLISH_WORK_KAMPALA_PARENTS__SCHOOL_2004.pdf"
      },
      {
        "title": "BABY-CLASS WRITING EXAM",
        "description": "Baby Class",
        "price": 5000,
        "pdfUrl": "https://freshteacher.software/BABY-CLASS WRITING EXAM.pdf"
      },
      {
        "title": "End_of_August_English_3_4_years_Exam",
        "description": "Baby Class",
        "price": 5000,
        "pdfUrl": "https://freshteacher.software/End_of_August_English_3_4_years_Exam.pdf"
      },
      {
        "title": "END_OF_AUGUST_HOLIDAY_WORK_literacy_3_4_years_Success_Integrated",
        "description": "Baby Class",
        "price": 5000,
        "pdfUrl": "https://freshteacher.software/END_OF_AUGUST_HOLIDAY_WORK_literacy_3_4_years_Success_Integrated.pdf"
      },
      {
        "title": "END_OF_AUGUST_HOLIDAY_WORK_numbers_3_4_years_Success_Integrated",
        "description": "Baby Class",
        "price": 5000,
        "pdfUrl": "https://freshteacher.software/END_OF_AUGUST_HOLIDAY_WORK_numbers_3_4_years_Success_Integrated.pdf"
      },
      {
        "title": "End-of-August-English-3-4-years-Exam-Success-Integrated-Nursery-School",
        "description": "Baby Class",
        "price": 5000,
        "pdfUrl": "https://freshteacher.software/End-of-August-English-3-4-years-Exam-Success-Integrated-Nursery-School.pdf"
      },
      {
        "title": "END-OF-AUGUST-HOLIDAY-WORK-numbers-3-4-years-Success-Integrated-Nursery-School",
        "description": "Baby Class",
        "price": 5000,
        "pdfUrl": "https://freshteacher.software/END-OF-AUGUST-HOLIDAY-WORK-numbers-3-4-years-Success-Integrated-Nursery-School.pdf"
      },
      {
        "title": "ENG I  BABY  CLASS EOT 1_out",
        "description": "Baby Class",
        "price": 5000,
        "pdfUrl": "https://freshteacher.software/ENG I  BABY  CLASS EOT 1_out.pdf"
      },
      {
        "title": "HOLIDAY PACKAGE FOR BABY CLASS",
        "description": "Baby Class",
        "price": 5000,
        "pdfUrl": "https://freshteacher.software/HOLIDAY PACKAGE FOR BABY CLASS.pdf"
      },
      {
        "title": "REVISION WORK ACTIVITIES FOR BABY",
        "description": "Baby Class",
        "price": 5000,
        "pdfUrl": "https://freshteacher.software/REVISION WORK ACTIVITIES FOR BABY.pdf"
      },
      {
        "title": "REVISION WORK FOR BABY CLASS",
        "description": "Baby Class",
        "price": 5000,
        "pdfUrl": "https://freshteacher.software/REVISION WORK FOR BABY CLASS.pdf"
      },
      {
        "title": "REVISION WORK FOR BABY",
        "description": "Baby Class",
        "price": 5000,
        "pdfUrl": "https://freshteacher.software/REVISION WORK FOR BABY.pdf"
      }
    ]