[
{
  "title": "",
  "description": "Senior Four",
  "price": 5000,
  "pdfUrl": "https://fresh-teacher.github.io/s4/FRENCH 2 O.pdf"
  },
  {
    "title": "",
    "description": "Senior Four",
    "price": 5000,
    "pdfUrl": "https://fresh-teacher.github.io/s4/FRENCH EXAM.pdf"
  },
  {
    "title": "",
    "description": "Senior Four",
    "price": 5000,
    "pdfUrl": "https://fresh-teacher.github.io/s4/S.2 FRENCH MOCK KING’S COLLEGE – BUDDO.pdf"
  },
  {
    "title": "",
    "description": "Senior Four",
    "price": 5000,
    "pdfUrl": "https://fresh-teacher.github.io/s4/s.4 french p.2 MOCK KING’S COLLEGE – BUDDO.pdf"
  },
  {
    "title": "",
    "description": "Senior Four",
    "price": 5000,
    "pdfUrl": "https://fresh-teacher.github.io/s4/S.4 FRENCH P314 INTERNAL MOCK KING’S COLLEGE – BUDDO.pdf"
  },
  {
    "title": "",
    "description": "Senior Four",
    "price": 5000,
    "pdfUrl": "https://fresh-teacher.github.io/s4/S.4-FRENCH-MID-TERM-ONE-EXAMINATION-2020.pdf"
  },
  {
    "title": "",
    "description": "Senior Four",
    "price": 5000,
    "pdfUrl": "https://fresh-teacher.github.io/s4/FRECH S.4 MOCK KING’S COLLEGE – BUDDO.pdf"
  }
]