[
{
  "title": "",
  "description": "Senior Six",
  "price": 5000,
  "pdfUrl": "https://fresh-teacher.github.io/s6/UTEC Geog3 marking guide.pdf"
  },
  {
    "title": "",
    "description": "Senior Six",
    "price": 5000,
    "pdfUrl": "https://fresh-teacher.github.io/s6/UTEC MOCK Geo 3.pdf"
  },
  {
    "title": "",
    "description": "Senior Six",
    "price": 5000,
    "pdfUrl": "https://fresh-teacher.github.io/s6/wakissha geography.pdf"
  },
  {
    "title": "",
    "description": "Senior Six",
    "price": 5000,
    "pdfUrl": "https://fresh-teacher.github.io/s6/WAKISSHA MOCK UACE GEOG MG.pdf"
  },
  {
    "title": "",
    "description": "Senior Six",
    "price": 5000,
    "pdfUrl": "https://fresh-teacher.github.io/s6/WAKISSHA UACE GEOG.pdf"
  },
  {
    "title": "",
    "description": "Senior Six",
    "price": 5000,
    "pdfUrl": "https://fresh-teacher.github.io/s6/WAKKISHA GUIDE S4 GROG2.pdf"
  },
  {
    "title": "",
    "description": "Senior Six",
    "price": 5000,
    "pdfUrl": "https://fresh-teacher.github.io/s6/3 UACE GEOG PP2.pdf"
  },
  {
    "title": "",
    "description": "Senior Six",
    "price": 5000,
    "pdfUrl": "https://fresh-teacher.github.io/s6/A. GEO P.1.pdf"
  },
  {
    "title": "",
    "description": "Senior Six",
    "price": 5000,
    "pdfUrl": "https://fresh-teacher.github.io/s6/A. GEO P3.pdf"
  },
  {
    "title": "",
    "description": "Senior Six",
    "price": 5000,
    "pdfUrl": "https://fresh-teacher.github.io/s6/A. GEOM. P3.pdf"
  },
  {
    "title": "",
    "description": "Senior Six",
    "price": 5000,
    "pdfUrl": "https://fresh-teacher.github.io/s6/Aitel Geog 3-1.pdf"
  },
  {
    "title": "",
    "description": "Senior Six",
    "price": 5000,
    "pdfUrl": "https://fresh-teacher.github.io/s6/A-LEVEL GEOGRAPHY P2501, 2&3 WAKISSHA 2023.pdf"
  },
  {
    "title": "",
    "description": "Senior Six",
    "price": 5000,
    "pdfUrl": "https://fresh-teacher.github.io/s6/ASSHU.Geo.1.pdf"
  },
  {
    "title": "",
    "description": "Senior Six",
    "price": 5000,
    "pdfUrl": "https://fresh-teacher.github.io/s6/BURJEB GEOG 3.pdf"
  },
  {
    "title": "",
    "description": "Senior Six",
    "price": 5000,
    "pdfUrl": "https://fresh-teacher.github.io/s6/Coastal Geomorphology.pdf"
  },
  {
    "title": "",
    "description": "Senior Six",
    "price": 5000,
    "pdfUrl": "https://fresh-teacher.github.io/s6/CONF. GEOG 1 MUKONO EXAMINATION COUNCIL.pdf"
  },
  {
    "title": "",
    "description": "Senior Six",
    "price": 5000,
    "pdfUrl": "https://fresh-teacher.github.io/s6/GEG 3 A level.pdf"
  },
  {
    "title": "",
    "description": "Senior Six",
    "price": 5000,
    "pdfUrl": "https://fresh-teacher.github.io/s6/GEO 3 2022 Uneb.pdf"
  },
  {
    "title": "",
    "description": "Senior Six",
    "price": 5000,
    "pdfUrl": "https://fresh-teacher.github.io/s6/GEO Pp1.pdf"
  },
  {
    "title": "",
    "description": "Senior Six",
    "price": 5000,
    "pdfUrl": "https://fresh-teacher.github.io/s6/GEO1 A WKSHA.pdf"
  },
  {
    "title": "",
    "description": "Senior Six",
    "price": 5000,
    "pdfUrl": "https://fresh-teacher.github.io/s6/GEO1 A WKSHA-1.pdf"
  },
  {
    "title": "",
    "description": "Senior Six",
    "price": 5000,
    "pdfUrl": "https://fresh-teacher.github.io/s6/GEO2 A WKSHA.pdf"
  },
  {
    "title": "",
    "description": "Senior Six",
    "price": 5000,
    "pdfUrl": "https://fresh-teacher.github.io/s6/geo2 kalussa.pdf"
  },
  {
    "title": "",
    "description": "Senior Six",
    "price": 5000,
    "pdfUrl": "https://fresh-teacher.github.io/s6/GEO3 WKSHA.pdf"
  },
  {
    "title": "",
    "description": "Senior Six",
    "price": 5000,
    "pdfUrl": "https://fresh-teacher.github.io/s6/GEOG 1 A.pdf"
  },
  {
    "title": "",
    "description": "Senior Six",
    "price": 5000,
    "pdfUrl": "https://fresh-teacher.github.io/s6/GEOG 1 MUKONO EXAMINATION COUNCIL.pdf"
  },
  {
    "title": "",
    "description": "Senior Six",
    "price": 5000,
    "pdfUrl": "https://fresh-teacher.github.io/s6/GEOG 1 RESOURCE 2022..pdf"
  },
  {
    "title": "",
    "description": "Senior Six",
    "price": 5000,
    "pdfUrl": "https://fresh-teacher.github.io/s6/GEOG 1 S6 Cleveland high.pdf"
  },
  {
    "title": "",
    "description": "Senior Six",
    "price": 5000,
    "pdfUrl": "https://fresh-teacher.github.io/s6/GEOG 1 S6 detailed @ff.pdf"
  },
  {
    "title": "",
    "description": "Senior Six",
    "price": 5000,
    "pdfUrl": "https://fresh-teacher.github.io/s6/GEOG 1 WESTERN JOINT MOCK EXAMINATIONS.pdf"
  },
  {
    "title": "",
    "description": "Senior Six",
    "price": 5000,
    "pdfUrl": "https://fresh-teacher.github.io/s6/GEOG 2 A chloropleth map.pdf"
  },
  {
    "title": "",
    "description": "Senior Six",
    "price": 5000,
    "pdfUrl": "https://fresh-teacher.github.io/s6/GEOG 2 A level.pdf"
  },
  {
    "title": "",
    "description": "Senior Six",
    "price": 5000,
    "pdfUrl": "https://fresh-teacher.github.io/s6/GEOG 2 A.pdf"
  },
  {
    "title": "",
    "description": "Senior Six",
    "price": 5000,
    "pdfUrl": "https://fresh-teacher.github.io/s6/Geog 2 BUGANDA EXAMINATIONS COUNCIL MOCKS 2019.pdf"
  },
  {
    "title": "",
    "description": "Senior Six",
    "price": 5000,
    "pdfUrl": "https://fresh-teacher.github.io/s6/GEOG 2 MUKONO EXAMINATION COUNCIL.pdf"
  },
  {
    "title": "",
    "description": "Senior Six",
    "price": 5000,
    "pdfUrl": "https://fresh-teacher.github.io/s6/GEOG 2 WESTERN JOINT MOCK EXAMINATIONS.pdf"
  },
  {
    "title": "",
    "description": "Senior Six",
    "price": 5000,
    "pdfUrl": "https://fresh-teacher.github.io/s6/GEOG 2-1.pdf"
  },
  {
    "title": "",
    "description": "Senior Six",
    "price": 5000,
    "pdfUrl": "https://fresh-teacher.github.io/s6/GEOG 3 A (2).pdf"
  },
  {
    "title": "",
    "description": "Senior Six",
    "price": 5000,
    "pdfUrl": "https://fresh-teacher.github.io/s6/GEOG 3 A.pdf"
  },
  {
    "title": "",
    "description": "Senior Six",
    "price": 5000,
    "pdfUrl": "https://fresh-teacher.github.io/s6/GEOG 3 ALEVEL.pdf"
  },
  {
    "title": "",
    "description": "Senior Six",
    "price": 5000,
    "pdfUrl": "https://fresh-teacher.github.io/s6/GEOG 3 INTERNAL MOCK 2022.pdf"
  },
  {
    "title": "",
    "description": "Senior Six",
    "price": 5000,
    "pdfUrl": "https://fresh-teacher.github.io/s6/GEOG 3 MUKONO EXAMINATION COUNCIL.pdf"
  },
  {
    "title": "",
    "description": "Senior Six",
    "price": 5000,
    "pdfUrl": "https://fresh-teacher.github.io/s6/GEOG 3 PA.pdf"
  },
  {
    "title": "",
    "description": "Senior Six",
    "price": 5000,
    "pdfUrl": "https://fresh-teacher.github.io/s6/GEOG 3 UACE BUGANDA EXAMINATIONS COUNCIL MOCKS 2019.pdf"
  },
  {
    "title": "",
    "description": "Senior Six",
    "price": 5000,
    "pdfUrl": "https://fresh-teacher.github.io/s6/GEOG 3 UACE GUIDE-3 RESOURSE MOCK 2019.pdf"
  },
  {
    "title": "",
    "description": "Senior Six",
    "price": 5000,
    "pdfUrl": "https://fresh-teacher.github.io/s6/GEOG 3 WESTERN JOINT MOCK EXAMINATIONS.pdf"
  },
  {
    "title": "",
    "description": "Senior Six",
    "price": 5000,
    "pdfUrl": "https://fresh-teacher.github.io/s6/geog 3kalussa.pdf"
  },
  {
    "title": "",
    "description": "Senior Six",
    "price": 5000,
    "pdfUrl": "https://fresh-teacher.github.io/s6/GEOG INTRODUCTION FORM ONE NOTES.pdf"
  },
  {
    "title": "",
    "description": "Senior Six",
    "price": 5000,
    "pdfUrl": "https://fresh-teacher.github.io/s6/GEOG OBJECTIVE QN BANK.pdf"
  },
  {
    "title": "",
    "description": "Senior Six",
    "price": 5000,
    "pdfUrl": "https://fresh-teacher.github.io/s6/GEOG PAPER 2.pdf"
  },
  {
    "title": "",
    "description": "Senior Six",
    "price": 5000,
    "pdfUrl": "https://fresh-teacher.github.io/s6/Geog Physical  pp1.pdf"
  },
  {
    "title": "",
    "description": "Senior Six",
    "price": 5000,
    "pdfUrl": "https://fresh-teacher.github.io/s6/Geog Pp 1 Confidential.pdf"
  },
  {
    "title": "",
    "description": "Senior Six",
    "price": 5000,
    "pdfUrl": "https://fresh-teacher.github.io/s6/Geog Pp1 S.6 ST. MARY_S KITENDE 2020.pdf"
  },
  {
    "title": "",
    "description": "Senior Six",
    "price": 5000,
    "pdfUrl": "https://fresh-teacher.github.io/s6/Geog Pp1 S.6 ST. MARY'S KITENDE 2020.pdf"
  },
  {
    "title": "",
    "description": "Senior Six",
    "price": 5000,
    "pdfUrl": "https://fresh-teacher.github.io/s6/Geog Pp2 S.6 ST. MARY_S KITENDE 2020.pdf"
  },
  {
    "title": "",
    "description": "Senior Six",
    "price": 5000,
    "pdfUrl": "https://fresh-teacher.github.io/s6/Geog Pp2 S.6 ST. MARY'S KITENDE 2020.pdf"
  },
  {
    "title": "",
    "description": "Senior Six",
    "price": 5000,
    "pdfUrl": "https://fresh-teacher.github.io/s6/Geog Pp2.pdf"
  },
  {
    "title": "",
    "description": "Senior Six",
    "price": 5000,
    "pdfUrl": "https://fresh-teacher.github.io/s6/Geog PP3 S.6 ST. MARY_S KITENDE 2020.pdf"
  },
  {
    "title": "",
    "description": "Senior Six",
    "price": 5000,
    "pdfUrl": "https://fresh-teacher.github.io/s6/Geog PP3 S.6 ST. MARY'S KITENDE 2020.pdf"
  },
  {
    "title": "",
    "description": "Senior Six",
    "price": 5000,
    "pdfUrl": "https://fresh-teacher.github.io/s6/Geog_1 UTEC MARKING GUIDE.pdf"
  },
  {
    "title": "",
    "description": "Senior Six",
    "price": 5000,
    "pdfUrl": "https://fresh-teacher.github.io/s6/Geog_2 UTEC MARKING GUIDE.pdf"
  },
  {
    "title": "",
    "description": "Senior Six",
    "price": 5000,
    "pdfUrl": "https://fresh-teacher.github.io/s6/Geog_3 UTEC MARKING GUIDE.pdf"
  },
  {
    "title": "",
    "description": "Senior Six",
    "price": 5000,
    "pdfUrl": "https://fresh-teacher.github.io/s6/GEOG-1-A.pdf"
  },
  {
    "title": "",
    "description": "Senior Six",
    "price": 5000,
    "pdfUrl": "https://fresh-teacher.github.io/s6/Geography 1 BUGANDA EXAMINATIONS COUNCIL MOCKS 2019.pdf"
  },
  {
    "title": "",
    "description": "Senior Six",
    "price": 5000,
    "pdfUrl": "https://fresh-teacher.github.io/s6/Geography 1 UTEB 2019.pdf"
  },
  {
    "title": "",
    "description": "Senior Six",
    "price": 5000,
    "pdfUrl": "https://fresh-teacher.github.io/s6/Geography 1.pdf"
  },
  {
    "title": "",
    "description": "Senior Six",
    "price": 5000,
    "pdfUrl": "https://fresh-teacher.github.io/s6/Geography 2 Alevel qn proportional divided circles.pdf"
  },
  {
    "title": "",
    "description": "Senior Six",
    "price": 5000,
    "pdfUrl": "https://fresh-teacher.github.io/s6/GEOGRAPHY 2 HOLIDAY PACKAGE.pdf"
  },
  {
    "title": "",
    "description": "Senior Six",
    "price": 5000,
    "pdfUrl": "https://fresh-teacher.github.io/s6/Geography 2 UTEB 2019.pdf"
  },
  {
    "title": "",
    "description": "Senior Six",
    "price": 5000,
    "pdfUrl": "https://fresh-teacher.github.io/s6/Geography 2.pdf"
  },
  {
    "title": "",
    "description": "Senior Six",
    "price": 5000,
    "pdfUrl": "https://fresh-teacher.github.io/s6/GEOGRAPHY 3 TEST.pdf"
  },
  {
    "title": "",
    "description": "Senior Six",
    "price": 5000,
    "pdfUrl": "https://fresh-teacher.github.io/s6/Geography 3 UTEB 2019.pdf"
  },
  {
    "title": "",
    "description": "Senior Six",
    "price": 5000,
    "pdfUrl": "https://fresh-teacher.github.io/s6/Geography 3.pdf"
  },
  {
    "title": "",
    "description": "Senior Six",
    "price": 5000,
    "pdfUrl": "https://fresh-teacher.github.io/s6/GEOGRAPHY ASSSIGNMENT..pdf"
  },
  {
    "title": "",
    "description": "Senior Six",
    "price": 5000,
    "pdfUrl": "https://fresh-teacher.github.io/s6/Geography Do it Your Self for A’level.pdf"
  },
  {
    "title": "",
    "description": "Senior Six",
    "price": 5000,
    "pdfUrl": "https://fresh-teacher.github.io/s6/GEOGRAPHY P250123WAKISSHA GUIDES 2022.pdf"
  },
  {
    "title": "",
    "description": "Senior Six",
    "price": 5000,
    "pdfUrl": "https://fresh-teacher.github.io/s6/GEOGRAPHY PAPER 2 REVISION.pdf"
  },
  {
    "title": "",
    "description": "Senior Six",
    "price": 5000,
    "pdfUrl": "https://fresh-teacher.github.io/s6/GEOGRAPHY S.6 INTERNAL MOCKS P.3 2019).pdf"
  },
  {
    "title": "",
    "description": "Senior Six",
    "price": 5000,
    "pdfUrl": "https://fresh-teacher.github.io/s6/Guide JJEB Geog 3 2022.pdf"
  },
  {
    "title": "",
    "description": "Senior Six",
    "price": 5000,
    "pdfUrl": "https://fresh-teacher.github.io/s6/JJEB GEOG 3 2022.pdf"
  },
  {
    "title": "",
    "description": "Senior Six",
    "price": 5000,
    "pdfUrl": "https://fresh-teacher.github.io/s6/KCSE GEO PP1 REVISION.pdf"
  },
  {
    "title": "",
    "description": "Senior Six",
    "price": 5000,
    "pdfUrl": "https://fresh-teacher.github.io/s6/Light Africa Post mock Geo 1.pdf"
  },
  {
    "title": "",
    "description": "Senior Six",
    "price": 5000,
    "pdfUrl": "https://fresh-teacher.github.io/s6/Macadita UACE Geog3 mock 2023.pdf"
  },
  {
    "title": "",
    "description": "Senior Six",
    "price": 5000,
    "pdfUrl": "https://fresh-teacher.github.io/s6/MATIGO GEO 1 UACE MARKING GUIDE.pdf"
  },
  {
    "title": "",
    "description": "Senior Six",
    "price": 5000,
    "pdfUrl": "https://fresh-teacher.github.io/s6/MATIGO MOCKS 2022 UACE GEOG PP1.pdf"
  },
  {
    "title": "",
    "description": "Senior Six",
    "price": 5000,
    "pdfUrl": "https://fresh-teacher.github.io/s6/MATIGO MOCKS 2022 UACE GEOG PP2.pdf"
  },
  {
    "title": "",
    "description": "Senior Six",
    "price": 5000,
    "pdfUrl": "https://fresh-teacher.github.io/s6/MATIGO MOCKS 2022 UACE GEOG PP2_220809_012234.pdf"
  },
  {
    "title": "",
    "description": "Senior Six",
    "price": 5000,
    "pdfUrl": "https://fresh-teacher.github.io/s6/MATIGO MOCKS 2022 UACE GEOG PP3.pdf"
  },
  {
    "title": "",
    "description": "Senior Six",
    "price": 5000,
    "pdfUrl": "https://fresh-teacher.github.io/s6/MATIGO MOCKS GEO 1 UACE 2023.pdf"
  },
  {
    "title": "",
    "description": "Senior Six",
    "price": 5000,
    "pdfUrl": "https://fresh-teacher.github.io/s6/MATIGO MOCKS GEO 2 UACE MARKING GUIDE 2023.pdf"
  },
  {
    "title": "",
    "description": "Senior Six",
    "price": 5000,
    "pdfUrl": "https://fresh-teacher.github.io/s6/MATIGO MOCKS GEO 3 UACE GUIDE 2023.pdf"
  },
  {
    "title": "",
    "description": "Senior Six",
    "price": 5000,
    "pdfUrl": "https://fresh-teacher.github.io/s6/MATIGO MOCKS UACE GEO 2 2023.pdf"
  },
  {
    "title": "",
    "description": "Senior Six",
    "price": 5000,
    "pdfUrl": "https://fresh-teacher.github.io/s6/MATIGO MOCKS UACE GEO PP3 2023.pdf"
  },
  {
    "title": "",
    "description": "Senior Six",
    "price": 5000,
    "pdfUrl": "https://fresh-teacher.github.io/s6/NAMUGONGO UACE GEOG SEMINAR.pdf"
  },
  {
    "title": "",
    "description": "Senior Six",
    "price": 5000,
    "pdfUrl": "https://fresh-teacher.github.io/s6/NSAMBYA.pdf"
  },
  {
    "title": "",
    "description": "Senior Six",
    "price": 5000,
    "pdfUrl": "https://fresh-teacher.github.io/s6/OCER UACE MOT 1 GEO P1.pdf"
  },
  {
    "title": "",
    "description": "Senior Six",
    "price": 5000,
    "pdfUrl": "https://fresh-teacher.github.io/s6/P250 Statistics.pdf"
  },
  {
    "title": "",
    "description": "Senior Six",
    "price": 5000,
    "pdfUrl": "https://fresh-teacher.github.io/s6/P250-1 #2022-20221123130528.pdf"
  },
  {
    "title": "",
    "description": "Senior Six",
    "price": 5000,
    "pdfUrl": "https://fresh-teacher.github.io/s6/P2501, 2&3 WAKISSHA 2023.pdf"
  },
  {
    "title": "",
    "description": "Senior Six",
    "price": 5000,
    "pdfUrl": "https://fresh-teacher.github.io/s6/s.6 geo p.3 KINGS COLLEGE BUDDO 2020.pdf"
  },
  {
    "title": "",
    "description": "Senior Six",
    "price": 5000,
    "pdfUrl": "https://fresh-teacher.github.io/s6/S.6 GEOG 1 ELITE 2019.pdf"
  },
  {
    "title": "",
    "description": "Senior Six",
    "price": 5000,
    "pdfUrl": "https://fresh-teacher.github.io/s6/S.6 GEOG 1 KINGS COLLEGE BUDDO 2020.pdf"
  },
  {
    "title": "",
    "description": "Senior Six",
    "price": 5000,
    "pdfUrl": "https://fresh-teacher.github.io/s6/S.6 GEOG 1 MOCK 2019.pdf"
  },
  {
    "title": "",
    "description": "Senior Six",
    "price": 5000,
    "pdfUrl": "https://fresh-teacher.github.io/s6/S.6 Geog 1 Notes - Coastal Geormophology.pdf"
  },
  {
    "title": "",
    "description": "Senior Six",
    "price": 5000,
    "pdfUrl": "https://fresh-teacher.github.io/s6/S.6 GEOG 2 ELITE 2019.pdf"
  },
  {
    "title": "",
    "description": "Senior Six",
    "price": 5000,
    "pdfUrl": "https://fresh-teacher.github.io/s6/S.6 GEOG 2 MOCK 2019.pdf"
  },
  {
    "title": "",
    "description": "Senior Six",
    "price": 5000,
    "pdfUrl": "https://fresh-teacher.github.io/s6/S.6 GEOG 3 ELITE 2019.pdf"
  },
  {
    "title": "",
    "description": "Senior Six",
    "price": 5000,
    "pdfUrl": "https://fresh-teacher.github.io/s6/S.6 GEOG 3 MOCK 2019.pdf"
  },
  {
    "title": "",
    "description": "Senior Six",
    "price": 5000,
    "pdfUrl": "https://fresh-teacher.github.io/s6/S.6 Geog notes - TRANSPORT   URBANISATION.docx.pdf"
  },
  {
    "title": "",
    "description": "Senior Six",
    "price": 5000,
    "pdfUrl": "https://fresh-teacher.github.io/s6/s.6 geog p.2 KINGS COLLEGE BUDDO 2020.pdf"
  },
  {
    "title": "",
    "description": "Senior Six",
    "price": 5000,
    "pdfUrl": "https://fresh-teacher.github.io/s6/S.6 GEOG P3 MOCK (ecolebooks.com).pdf"
  },
  {
    "title": "",
    "description": "Senior Six",
    "price": 5000,
    "pdfUrl": "https://fresh-teacher.github.io/s6/S.6 GEOG P250.2, COMPLETE GUIDE,By Tr Mwirumubi.pdf"
  },
  {
    "title": "",
    "description": "Senior Six",
    "price": 5000,
    "pdfUrl": "https://fresh-teacher.github.io/s6/S.6 Geog PP2  UNASE 2019.pdf"
  },
  {
    "title": "",
    "description": "Senior Six",
    "price": 5000,
    "pdfUrl": "https://fresh-teacher.github.io/s6/S.6 Geog Pp3 UNASE 2019.pdf"
  },
  {
    "title": "",
    "description": "Senior Six",
    "price": 5000,
    "pdfUrl": "https://fresh-teacher.github.io/s6/S.6 GEOG UTILIZATION AND CONSERVATION OF NATURAL RESOURCES_2.pdf"
  },
  {
    "title": "",
    "description": "Senior Six",
    "price": 5000,
    "pdfUrl": "https://fresh-teacher.github.io/s6/S.6 GEOGRAPHY  Rhine NOTES.pdf"
  },
  {
    "title": "",
    "description": "Senior Six",
    "price": 5000,
    "pdfUrl": "https://fresh-teacher.github.io/s6/S.6 GEOGRAPHY 1.pdf"
  },
  {
    "title": "",
    "description": "Senior Six",
    "price": 5000,
    "pdfUrl": "https://fresh-teacher.github.io/s6/S.6 GEOGRAPHY 2.pdf"
  },
  {
    "title": "",
    "description": "Senior Six",
    "price": 5000,
    "pdfUrl": "https://fresh-teacher.github.io/s6/S.6 GEOGRAPHY 3 WORK.pdf"
  },
  {
    "title": "",
    "description": "Senior Six",
    "price": 5000,
    "pdfUrl": "https://fresh-teacher.github.io/s6/S.6 GEOGRAPHY 3.pdf"
  },
  {
    "title": "",
    "description": "Senior Six",
    "price": 5000,
    "pdfUrl": "https://fresh-teacher.github.io/s6/S.6 GEOGRAPHY Forestry NOTES.pdf"
  },
  {
    "title": "",
    "description": "Senior Six",
    "price": 5000,
    "pdfUrl": "https://fresh-teacher.github.io/s6/S.6 GEOGRAPHY P1 MOCK 1 (ecolebooks.com).pdf"
  },
  {
    "title": "",
    "description": "Senior Six",
    "price": 5000,
    "pdfUrl": "https://fresh-teacher.github.io/s6/S.6 GEOGRAPHY settlements NOTES.pdf"
  },
  {
    "title": "",
    "description": "Senior Six",
    "price": 5000,
    "pdfUrl": "https://fresh-teacher.github.io/s6/S.6 PAPER 1 SHARED.pdf"
  },
  {
    "title": "",
    "description": "Senior Six",
    "price": 5000,
    "pdfUrl": "https://fresh-teacher.github.io/s6/S.6-GEO-1-NOTES.pdf"
  },
  {
    "title": "",
    "description": "Senior Six",
    "price": 5000,
    "pdfUrl": "https://fresh-teacher.github.io/s6/S.6-GEO-3-EXAMS.pdf"
  },
  {
    "title": "",
    "description": "Senior Six",
    "price": 5000,
    "pdfUrl": "https://fresh-teacher.github.io/s6/S.6-GEO-3-FIELD-WORK.pdf"
  },
  {
    "title": "",
    "description": "Senior Six",
    "price": 5000,
    "pdfUrl": "https://fresh-teacher.github.io/s6/S.6-GEOG-1-Notes.pdf"
  },
  {
    "title": "",
    "description": "Senior Six",
    "price": 5000,
    "pdfUrl": "https://fresh-teacher.github.io/s6/S.6-GEOG-2-EXAM.pdf"
  },
  {
    "title": "",
    "description": "Senior Six",
    "price": 5000,
    "pdfUrl": "https://fresh-teacher.github.io/s6/S.6-GEOGRAPHY-1-NOTES.pdf"
  },
  {
    "title": "",
    "description": "Senior Six",
    "price": 5000,
    "pdfUrl": "https://fresh-teacher.github.io/s6/S.6-GEOGRAPHY-1-TEST-1 (2).pdf"
  },
  {
    "title": "",
    "description": "Senior Six",
    "price": 5000,
    "pdfUrl": "https://fresh-teacher.github.io/s6/S.6-GEOGRAPHY-1-TEST-1.pdf"
  },
  {
    "title": "",
    "description": "Senior Six",
    "price": 5000,
    "pdfUrl": "https://fresh-teacher.github.io/s6/S.6-GEOGRAPHY-1-WORK.pdf"
  },
  {
    "title": "",
    "description": "Senior Six",
    "price": 5000,
    "pdfUrl": "https://fresh-teacher.github.io/s6/S6 GEO 1 KAMOTA 2023.pdf"
  },
  {
    "title": "",
    "description": "Senior Six",
    "price": 5000,
    "pdfUrl": "https://fresh-teacher.github.io/s6/S6 Geog (Coastal Geomorphology).pdf"
  },
  {
    "title": "",
    "description": "Senior Six",
    "price": 5000,
    "pdfUrl": "https://fresh-teacher.github.io/s6/S6 Geog (Transport).pdf"
  },
  {
    "title": "",
    "description": "Senior Six",
    "price": 5000,
    "pdfUrl": "https://fresh-teacher.github.io/s6/S6 Geog 2 homework.pdf"
  },
  {
    "title": "",
    "description": "Senior Six",
    "price": 5000,
    "pdfUrl": "https://fresh-teacher.github.io/s6/S6 GEOG 2 RESOURSE MOCK 2019.pdf"
  },
  {
    "title": "",
    "description": "Senior Six",
    "price": 5000,
    "pdfUrl": "https://fresh-teacher.github.io/s6/S6 Geog 3 notes.pdf"
  },
  {
    "title": "",
    "description": "Senior Six",
    "price": 5000,
    "pdfUrl": "https://fresh-teacher.github.io/s6/S6 Geog 3 RESOURSE MOCK 2019.pdf"
  },
  {
    "title": "",
    "description": "Senior Six",
    "price": 5000,
    "pdfUrl": "https://fresh-teacher.github.io/s6/S6 GEOG PP2 KAMOTA 2023.pdf"
  },
  {
    "title": "",
    "description": "Senior Six",
    "price": 5000,
    "pdfUrl": "https://fresh-teacher.github.io/s6/S6 GEOG PP3 KAMOTA 2023.pdf"
  },
  {
    "title": "",
    "description": "Senior Six",
    "price": 5000,
    "pdfUrl": "https://fresh-teacher.github.io/s6/S6 GEOG TRANSPORT   URBANISATION.pdf"
  },
  {
    "title": "",
    "description": "Senior Six",
    "price": 5000,
    "pdfUrl": "https://fresh-teacher.github.io/s6/S6 GEOGRAPHY - STATISTICS.pdf"
  },
  {
    "title": "",
    "description": "Senior Six",
    "price": 5000,
    "pdfUrl": "https://fresh-teacher.github.io/s6/S6 GEOGRAPHY (physical).pdf"
  },
  {
    "title": "",
    "description": "Senior Six",
    "price": 5000,
    "pdfUrl": "https://fresh-teacher.github.io/s6/S6 Geography p1.pdf"
  },
  {
    "title": "",
    "description": "Senior Six",
    "price": 5000,
    "pdfUrl": "https://fresh-teacher.github.io/s6/S6 Geography p2.pdf"
  },
  {
    "title": "",
    "description": "Senior Six",
    "price": 5000,
    "pdfUrl": "https://fresh-teacher.github.io/s6/S6 Geography P3.pdf"
  },
  {
    "title": "",
    "description": "Senior Six",
    "price": 5000,
    "pdfUrl": "https://fresh-teacher.github.io/s6/S6 GEOGRAPHY PAPER 3 MOCK EXAMINATIONS.pdf"
  },
  {
    "title": "",
    "description": "Senior Six",
    "price": 5000,
    "pdfUrl": "https://fresh-teacher.github.io/s6/S6 GEOGRAPHY PAPER 3 MOCKS EXAMINATIONS UGANDA TEACHERS EDUCATION CONSULT(UTEC) 2022..pdf"
  },
  {
    "title": "",
    "description": "Senior Six",
    "price": 5000,
    "pdfUrl": "https://fresh-teacher.github.io/s6/S6 MOCK 2019 GEOGRAPHY P1 (ecolebooks.com).pdf"
  },
  {
    "title": "",
    "description": "Senior Six",
    "price": 5000,
    "pdfUrl": "https://fresh-teacher.github.io/s6/S6 MOCK 2019 GEOGRAPHY P2 (ecolebooks.com).pdf"
  },
  {
    "title": "",
    "description": "Senior Six",
    "price": 5000,
    "pdfUrl": "https://fresh-teacher.github.io/s6/S6 PAPER TWO GEOGRAPHY QUESTIONS(0).pdf"
  },
  {
    "title": "",
    "description": "Senior Six",
    "price": 5000,
    "pdfUrl": "https://fresh-teacher.github.io/s6/S6 PAPER TWO GEOGRAPHY QUESTIONS.pdf"
  },
  {
    "title": "",
    "description": "Senior Six",
    "price": 5000,
    "pdfUrl": "https://fresh-teacher.github.io/s6/S6-GEO-PAPER-1-EXAM.pdf"
  },
  {
    "title": "",
    "description": "Senior Six",
    "price": 5000,
    "pdfUrl": "https://fresh-teacher.github.io/s6/SECTION C GEOG1.pdf"
  },
  {
    "title": "",
    "description": "Senior Six",
    "price": 5000,
    "pdfUrl": "https://fresh-teacher.github.io/s6/TEST FRIDAY 17 2023 S.5 GEOG1 OCJC-1.pdf"
  },
  {
    "title": "",
    "description": "Senior Six",
    "price": 5000,
    "pdfUrl": "https://fresh-teacher.github.io/s6/U.A.C.E P250-2 2022-20221123173010.pdf"
  },
  {
    "title": "",
    "description": "Senior Six",
    "price": 5000,
    "pdfUrl": "https://fresh-teacher.github.io/s6/UACE 2022 250 paper one.pdf"
  },
  {
    "title": "",
    "description": "Senior Six",
    "price": 5000,
    "pdfUrl": "https://fresh-teacher.github.io/s6/UACE 2023 P1.pdf"
  },
  {
    "title": "",
    "description": "Senior Six",
    "price": 5000,
    "pdfUrl": "https://fresh-teacher.github.io/s6/UACE BUSOGA REGION JOINT EXAMINATION BOARD 2019  GEOGRAPHY paper3.pdf"
  },
  {
    "title": "",
    "description": "Senior Six",
    "price": 5000,
    "pdfUrl": "https://fresh-teacher.github.io/s6/UACE GEO MATIGO MOCKS GUIDE 2022.pdf"
  },
  {
    "title": "",
    "description": "Senior Six",
    "price": 5000,
    "pdfUrl": "https://fresh-teacher.github.io/s6/UACE GEO PP MARKING GUIDE 2022.pdf"
  },
  {
    "title": "",
    "description": "Senior Six",
    "price": 5000,
    "pdfUrl": "https://fresh-teacher.github.io/s6/UACE GEOG 1 2020.pdf"
  },
  {
    "title": "",
    "description": "Senior Six",
    "price": 5000,
    "pdfUrl": "https://fresh-teacher.github.io/s6/UACE GEOG 1 P250 PAHISCO.pdf"
  },
  {
    "title": "",
    "description": "Senior Six",
    "price": 5000,
    "pdfUrl": "https://fresh-teacher.github.io/s6/UACE GEOG PAPER1.pdf"
  },
  {
    "title": "",
    "description": "Senior Six",
    "price": 5000,
    "pdfUrl": "https://fresh-teacher.github.io/s6/UACE GEOG PAPER3.pdf"
  },
  {
    "title": "",
    "description": "Senior Six",
    "price": 5000,
    "pdfUrl": "https://fresh-teacher.github.io/s6/UACE GEOG PP2 GUIDE MATIGO MOCKS.pdf"
  },
  {
    "title": "",
    "description": "Senior Six",
    "price": 5000,
    "pdfUrl": "https://fresh-teacher.github.io/s6/UACE Geog3.pdf"
  },
  {
    "title": "",
    "description": "Senior Six",
    "price": 5000,
    "pdfUrl": "https://fresh-teacher.github.io/s6/UACE Geograph 2.pdf"
  },
  {
    "title": "",
    "description": "Senior Six",
    "price": 5000,
    "pdfUrl": "https://fresh-teacher.github.io/s6/UACE Geography 3.pdf"
  },
  {
    "title": "",
    "description": "Senior Six",
    "price": 5000,
    "pdfUrl": "https://fresh-teacher.github.io/s6/UACE Geography1.pdf"
  },
  {
    "title": "",
    "description": "Senior Six",
    "price": 5000,
    "pdfUrl": "https://fresh-teacher.github.io/s6/UACE Geography1-1.pdf"
  },
  {
    "title": "",
    "description": "Senior Six",
    "price": 5000,
    "pdfUrl": "https://fresh-teacher.github.io/s6/UACE JJEB P245-4 GUIDE 2022.pdf"
  },
  {
    "title": "",
    "description": "Senior Six",
    "price": 5000,
    "pdfUrl": "https://fresh-teacher.github.io/s6/UACE JJEB P250-1 geog GUIDE 2022.pdf"
  },
  {
    "title": "",
    "description": "Senior Six",
    "price": 5000,
    "pdfUrl": "https://fresh-teacher.github.io/s6/UACE JJEB P250-2 geog  Guide 2022.pdf"
  },
  {
    "title": "",
    "description": "Senior Six",
    "price": 5000,
    "pdfUrl": "https://fresh-teacher.github.io/s6/UACE JJEB P250-3 GUIDE 2022.pdf"
  },
  {
    "title": "",
    "description": "Senior Six",
    "price": 5000,
    "pdfUrl": "https://fresh-teacher.github.io/s6/UACE newvision 27June Geography Economics Literature ICT.pdf"
  },
  {
    "title": "",
    "description": "Senior Six",
    "price": 5000,
    "pdfUrl": "https://fresh-teacher.github.io/s6/UACE UMTA MOCK 2023 GEOG1.pdf"
  },
  {
    "title": "",
    "description": "Senior Six",
    "price": 5000,
    "pdfUrl": "https://fresh-teacher.github.io/s6/UACE22 Geo3.pdf"
  },
  {
    "title": "",
    "description": "Senior Six",
    "price": 5000,
    "pdfUrl": "https://fresh-teacher.github.io/s6/UACE-Geo-1-Past-papers.pdf"
  },
  {
    "title": "",
    "description": "Senior Six",
    "price": 5000,
    "pdfUrl": "https://fresh-teacher.github.io/s6/UACE-GEO-2-Past-papers.pdf"
  },
  {
    "title": "",
    "description": "Senior Six",
    "price": 5000,
    "pdfUrl": "https://fresh-teacher.github.io/s6/UACE-GEO-3-Past-papers.pdf"
  },
  {
    "title": "",
    "description": "Senior Six",
    "price": 5000,
    "pdfUrl": "https://fresh-teacher.github.io/s6/UMTA GEO2 A.pdf"
  },
  {
    "title": "",
    "description": "Senior Six",
    "price": 5000,
    "pdfUrl": "https://fresh-teacher.github.io/s6/UMTA MG GEOG 1.pdf"
  },
  {
    "title": "",
    "description": "Senior Six",
    "price": 5000,
    "pdfUrl": "https://fresh-teacher.github.io/s6/UMTA MG GEOG 2.pdf"
  },
  {
    "title": "",
    "description": "Senior Six",
    "price": 5000,
    "pdfUrl": "https://fresh-teacher.github.io/s6/UMTA MOCK geog2.pdf"
  },
  {
    "title": "",
    "description": "Senior Six",
    "price": 5000,
    "pdfUrl": "https://fresh-teacher.github.io/s6/UMUTA 2023 Geography2.pdf"
  },
  {
    "title": "",
    "description": "Senior Six",
    "price": 5000,
    "pdfUrl": "https://fresh-teacher.github.io/s6/UNEB UACE GEO P3 2022.pdf"
  },
  {
    "title": "",
    "description": "Senior Six",
    "price": 5000,
    "pdfUrl": "https://fresh-teacher.github.io/s6/UNEB-UACE-GEOGRAPHY-2017.pdf"
  },
  {
    "title": "",
    "description": "Senior Six",
    "price": 5000,
    "pdfUrl": "https://fresh-teacher.github.io/s6/UNEB-UACE-GEOGRAPHY-2018.pdf"
  },
  {
    "title": "",
    "description": "Senior Six",
    "price": 5000,
    "pdfUrl": "https://fresh-teacher.github.io/s6/UNMSS Namugongo A' level geography 2022 seminar guide.pdf"
  },
  {
    "title": "",
    "description": "Senior Six",
    "price": 5000,
    "pdfUrl": "https://fresh-teacher.github.io/s6/UTEB Geog 1 2019.pdf"
  },
  {
    "title": "",
    "description": "Senior Six",
    "price": 5000,
    "pdfUrl": "https://fresh-teacher.github.io/s6/UTEC GEOG 1.pdf"
  },
  {
    "title": "",
    "description": "Senior Six",
    "price": 5000,
    "pdfUrl": "https://fresh-teacher.github.io/s6/UTEC GEOG 2.pdf"
  },
  {
    "title": "",
    "description": "Senior Six",
    "price": 5000,
    "pdfUrl": "https://fresh-teacher.github.io/s6/UTEC GEOG 3.pdf"
  }
]